PythonShenduXuexiJiagouShiyongZhinanChuyi/README.md
PythonShenduXuexiJiagouShiyongZhinanChuyi/__init__.py
PythonShenduXuexiJiagouShiyongZhinanChuyi/__main__.py
PythonShenduXuexiJiagouShiyongZhinanChuyi/file.epub
PythonShenduXuexiJiagouShiyongZhinanChuyi/index.html
PythonShenduXuexiJiagouShiyongZhinanChuyi/css/__init__.py
PythonShenduXuexiJiagouShiyongZhinanChuyi/css/annotations.css
PythonShenduXuexiJiagouShiyongZhinanChuyi/css/main.css
PythonShenduXuexiJiagouShiyongZhinanChuyi/css/normalize.css
PythonShenduXuexiJiagouShiyongZhinanChuyi/css/popup.css
PythonShenduXuexiJiagouShiyongZhinanChuyi/font/__init__.py
PythonShenduXuexiJiagouShiyongZhinanChuyi/font/fontello.eot
PythonShenduXuexiJiagouShiyongZhinanChuyi/font/fontello.svg
PythonShenduXuexiJiagouShiyongZhinanChuyi/font/fontello.ttf
PythonShenduXuexiJiagouShiyongZhinanChuyi/font/fontello.woff
PythonShenduXuexiJiagouShiyongZhinanChuyi/img/__init__.py
PythonShenduXuexiJiagouShiyongZhinanChuyi/img/annotator-glyph-sprite.png
PythonShenduXuexiJiagouShiyongZhinanChuyi/img/annotator-icon-sprite.png
PythonShenduXuexiJiagouShiyongZhinanChuyi/img/apple-touch-icon.png
PythonShenduXuexiJiagouShiyongZhinanChuyi/img/cancelfullscreen.png
PythonShenduXuexiJiagouShiyongZhinanChuyi/img/close.png
PythonShenduXuexiJiagouShiyongZhinanChuyi/img/fullscreen.png
PythonShenduXuexiJiagouShiyongZhinanChuyi/img/loader.gif
PythonShenduXuexiJiagouShiyongZhinanChuyi/img/menu-icon.png
PythonShenduXuexiJiagouShiyongZhinanChuyi/img/save.png
PythonShenduXuexiJiagouShiyongZhinanChuyi/img/saved.png
PythonShenduXuexiJiagouShiyongZhinanChuyi/img/settings-s.png
PythonShenduXuexiJiagouShiyongZhinanChuyi/img/settings.png
PythonShenduXuexiJiagouShiyongZhinanChuyi/img/star.png
PythonShenduXuexiJiagouShiyongZhinanChuyi/js/__init__.py
PythonShenduXuexiJiagouShiyongZhinanChuyi/js/epub.js
PythonShenduXuexiJiagouShiyongZhinanChuyi/js/epub.min.js
PythonShenduXuexiJiagouShiyongZhinanChuyi/js/epub.min.map
PythonShenduXuexiJiagouShiyongZhinanChuyi/js/hooks.min.js
python_shendu_xuexi_jiagou_shiyong_zhinan_chuyi-2024.3.6.0.dist-info/METADATA
python_shendu_xuexi_jiagou_shiyong_zhinan_chuyi-2024.3.6.0.dist-info/WHEEL
python_shendu_xuexi_jiagou_shiyong_zhinan_chuyi-2024.3.6.0.dist-info/entry_points.txt
python_shendu_xuexi_jiagou_shiyong_zhinan_chuyi-2024.3.6.0.dist-info/top_level.txt
python_shendu_xuexi_jiagou_shiyong_zhinan_chuyi-2024.3.6.0.dist-info/RECORD
